{
	"localeFilter": {
		"filterType": "locale",
		"includeChildren": false,
		"whitelist": [
			"ca",
			"da_DK",
			"de_DE",
			"en_US",
			"es",
			"es_MX",
			"fi_FI",
			"fr",
			"fr_CA",
			"it",
			"ja",
			"nb_NO",
			"nl",
			"pt_PT",
			"pt_BR",
			"sv_SE",
			"tr",
			"zh-CN",
			"zh-HK",
			"zh-TW"
		 ]
	},
	"featureFilters": {
		"conversion_mappings": {
			"filterType": "regex",
			"blacklist": [
				"^ibm*"
			]
		},
		"confusables": {
			"filterType": "exclude"
		},
		"curr_tree": {
			"filterType": "exclude"
		},
		"unit_tree": {
			"filterType": "exclude"
		},
		"zone_tree": {
			"filterType": "exclude"
		},
		"unames": {
			"filterType": "exclude"
		}
	}
}
